ailia_speech/LICENSE_AILIA_EN.pdf
ailia_speech/LICENSE_AILIA_JA.pdf
ailia_speech/__init__.py
ailia_speech/linux/arm64-v8a/libailia_speech.so
ailia_speech/linux/x64/libailia_speech.so
ailia_speech/mac/libailia_speech.dylib
ailia_speech/windows/x64/ailia_speech.dll
ailia_speech-1.5.2.data/scripts/__init__.py
ailia_speech-1.5.2.dist-info/METADATA
ailia_speech-1.5.2.dist-info/WHEEL
ailia_speech-1.5.2.dist-info/top_level.txt
ailia_speech-1.5.2.dist-info/RECORD
